autoupgrade/__init__.py
autoupgrade_prima-0.6.5.dist-info/LICENSE.md
autoupgrade_prima-0.6.5.dist-info/METADATA
autoupgrade_prima-0.6.5.dist-info/WHEEL
autoupgrade_prima-0.6.5.dist-info/top_level.txt
autoupgrade_prima-0.6.5.dist-info/zip-safe
autoupgrade_prima-0.6.5.dist-info/RECORD
