Metadata-Version: 2.1
Name: autoupgrade-prima
Version: 0.6.5
Summary: Automatic upgrade of PyPI packages
Home-page: https://github.com/primait/autoupgrade
Download-URL: https://github.com/primait/autoupgrade/releases
Author: Walter Purcaro
Author-email: vuolter@gmail.com
License: MIT License
Keywords: autoupgrade,pip-upgrade,pip
Classifier: Development Status :: 5 - Production/Stable
Classifier: Environment :: Other Environment
Classifier: License :: OSI Approved :: MIT License
Classifier: Intended Audience :: Developers
Classifier: Intended Audience :: System Administrators
Classifier: Operating System :: OS Independent
Classifier: Programming Language :: Python
Classifier: Programming Language :: Python :: 2
Classifier: Programming Language :: Python :: 3
Classifier: Topic :: System :: Software Distribution
Classifier: Topic :: Utilities
Obsoletes: autoupgrade
License-File: LICENSE.md
Requires-Dist: semver
